README.md
s3imageresizer.py
setup.py
s3imageresizer.egg-info/PKG-INFO
s3imageresizer.egg-info/SOURCES.txt
s3imageresizer.egg-info/dependency_links.txt
s3imageresizer.egg-info/requires.txt
s3imageresizer.egg-info/top_level.txt