Metadata-Version: 2.1
Name: s3imageresizer
Version: 0.0.23
Summary: Import and resize pictures into amazon S3 storage
Home-page: https://github.com/erwan-lemonnier/s3imageresizer
Author: Erwan Lemonnier
Author-email: erwan@lemonnier.se
License: BSD
Platform: any
Classifier: Environment :: Web Environment
Classifier: Intended Audience :: Developers
Classifier: License :: OSI Approved :: BSD License
Classifier: Operating System :: OS Independent
Classifier: Programming Language :: Python
Classifier: Topic :: Internet :: WWW/HTTP :: Dynamic Content
Classifier: Topic :: Software Development :: Libraries :: Python Modules
